Workbook
Name NativeTimeline_Order_Date: #N/A
Name Slicer_Loyalty_Card: #N/A
Name Slicer_Roast_Type_Full_Name: #N/A
Name Slicer_Size: #N/A

Sheet Dashboard

Sheet SalesOverTime
A3: Sum of Sales | C3: Coffee Type Full Name
A4: Years | B4: Order Date | C4: Arabica | D4: Excelsa | E4: Liberica | F4: Robusta
A5: 2019 | B5: Jan | C5: 186.855 | D5: 305.97 | E5: 213.16 | F5: 123
B6: Feb | C6: 251.965 | D6: 129.46 | E6: 434.04 | F6: 171.94
B7: Mar | C7: 224.945 | D7: 349.12 | E7: 321.04 | F7: 126.035
B8: Apr | C8: 307.12 | D8: 681.075 | E8: 533.705 | F8: 158.85
B9: May | C9: 53.665 | D9: 83.025 | E9: 193.835 | F9: 68.04
B10: Jun | C10: 163.02 | D10: 678.36 | E10: 171.045 | F10: 372.255
B11: Jul | C11: 345.02 | D11: 273.87 | E11: 184.13 | F11: 201.115
B12: Aug | C12: 334.89 | D12: 70.95 | E12: 134.23 | F12: 166.275
B13: Sep | C13: 178.71 | D13: 166.1 | E13: 439.31 | F13: 492.9
B14: Oct | C14: 301.985 | D14: 153.765 | E14: 215.555 | F14: 213.665
B15: Nov | C15: 312.835 | D15: 63.25 | E15: 350.895 | F15: 96.405
B16: Dec | C16: 265.62 | D16: 526.515 | E16: 187.06 | F16: 210.59
A17: 2020 | B17: Jan | C17: 47.25 | D17: 65.805 | E17: 274.675 | F17: 179.22
B18: Feb | C18: 745.45 | D18: 428.885 | E18: 194.175 | F18: 429.83
B19: Mar | C19: 130.47 | D19: 271.485 | E19: 281.205 | F19: 231.63
B20: Apr | C20: 27 | D20: 347.26 | E20: 147.51 | F20: 240.04
B21: May | C21: 255.115 | D21: 541.73 | E21: 83.43 | F21: 59.08
B22: Jun | C22: 584.79 | D22: 357.43 | E22: 355.34 | F22: 140.88
B23: Jul | C23: 430.62 | D23: 227.425 | E23: 236.315 | F23: 414.585
B24: Aug | C24: 22.5 | D24: 77.72 | E24: 60.5 | F24: 139.68
B25: Sep | C25: 126.15 | D25: 195.11 | E25: 89.13 | F25: 302.66
B26: Oct | C26: 376.03 | D26: 523.24 | E26: 440.965 | F26: 174.47
B27: Nov | C27: 515.18 | D27: 142.56 | E27: 347.04 | F27: 104.085
B28: Dec | C28: 95.86 | D28: 484.76 | E28: 94.17 | F28: 77.105
A29: 2021 | B29: Jan | C29: 258.345 | D29: 139.625 | E29: 279.52 | F29: 160.195
B30: Feb | C30: 342.2 | D30: 284.25 | E30: 251.83 | F30: 80.55
B31: Mar | C31: 418.305 | D31: 468.125 | E31: 405.055 | F31: 253.155
B32: Apr | C32: 102.33 | D32: 242.14 | E32: 554.875 | F32: 106.24
B33: May | C33: 234.72 | D33: 133.08 | E33: 267.2 | F33: 272.69
B34: Jun | C34: 430.39 | D34: 136.205 | E34: 209.6 | F34: 88.335
B35: Jul | C35: 109.005 | D35: 393.575 | E35: 61.035 | F35: 199.49
B36: Aug | C36: 287.525 | D36: 288.67 | E36: 125.58 | F36: 374.135
B37: Sep | C37: 840.93 | D37: 409.875 | E37: 171.33 | F37: 221.44
B38: Oct | C38: 299.07 | D38: 260.325 | E38: 584.64 | F38: 256.365
B39: Nov | C39: 323.325 | D39: 565.57 | E39: 537.81 | F39: 189.475
B40: Dec | C40: 399.485 | D40: 148.2 | E40: 388.22 | F40: 212.075
A41: 2022 | B41: Jan | C41: 112.695 | D41: 166.32 | E41: 843.715 | F41: 146.685
B42: Feb | C42: 114.88 | D42: 133.815 | E42: 91.175 | F42: 53.76
B43: Mar | C43: 277.76 | D43: 175.41 | E43: 462.51 | F43: 399.525
B44: Apr | C44: 197.895 | D44: 289.755 | E44: 88.545 | F44: 200.255
B45: May | C45: 193.115 | D45: 212.495 | E45: 292.29 | F45: 304.47
B46: Jun | C46: 179.79 | D46: 426.2 | E46: 170.09 | F46: 379.31
B47: Jul | C47: 247.29 | D47: 246.685 | E47: 271.055 | F47: 141.7
B48: Aug | C48: 116.395 | D48: 41.25 | E48: 15.54 | F48: 71.06

Sheet SalesByCountry
A3: Country | B3: Sum of Sales
A4: United Kingdom | B4: 2798.505
A5: Ireland | B5: 6696.865
A6: United States | B6: 35638.885

Sheet SalesByCustomer
A3: Customer Name | B3: Sum of Sales
A4: Don Flintiff | B4: 278.01
A5: Nealson Cuttler | B5: 281.675
A6: Terri Farra | B6: 289.11
A7: Brenn Dundredge | B7: 307.045
A8: Allis Wilmore | B8: 317.07

Sheet orders
A1: Order ID | B1: Order Date | C1: Customer ID | D1: Product ID | E1: Quantity | F1: Customer Name | G1: Country | H1: Coffee Type | I1: Roast Type | J1: Size | K1: Unit Price | L1: Sales | M1: Coffee Type Full Name | N1: Roast Type Full Name | O1: Loyalty Card
A2: QEV-37451-860 | B2: 43713 | C2: 17670-51384-MA | D2: R-M-1 | E2: 2 | F2: =_xlfn.XLOOKUP(C2,customers!$A$2:$A$1001,customers!$B$2:$B$1001,,0) -> Aloisia Allner | G2: =_xlfn.XLOOKUP(C2,customers!$A$2:$A$1001,customers!$G$2:$G$1001,,0) -> United States | H2: =INDEX(products!$A$1:$G$49,MATCH(orders!$D2,products!$A$1:$A$49,0),MATCH(orders!H$1,products!$A$1:$G$1,0)) -> Rob | I2: =INDEX(products!$A$1:$G$49,MATCH(orders!$D2,products!$A$1:$A$49,0),MATCH(orders!I$1,products!$A$1:$G$1,0)) -> M | J2: =INDEX(products!$A$1:$G$49,MATCH(orders!$D2,products!$A$1:$A$49,0),MATCH(orders!J$1,products!$A$1:$G$1,0)) -> 1 | K2: =INDEX(products!$A$1:$G$49,MATCH(orders!$D2,products!$A$1:$A$49,0),MATCH(orders!K$1,products!$A$1:$G$1,0)) -> 9.95 | L2: =K2*E2 -> 19.9 | M2: {=_xlfn.IFS(H2="Rob","Robusta",H2="Exc","Excelsa",H2="Ara","Arabica",H2="Lib","Liberica")} -> Robusta | N2: {=_xlfn.IFS(I2="M","Medium",I2="L","Light",I2="D","Dark")} -> Medium | O2: =_xlfn.XLOOKUP(Orders[[#This Row],[Customer ID]],customers!$A$2:$A$1001,customers!$I$2:$I$1001,,0) -> Yes
A3: QEV-37451-860 | B3: 43713 | C3: 17670-51384-MA | D3: E-M-0.5 | E3: 5 | F3: =_xlfn.XLOOKUP(C3,customers!$A$2:$A$1001,customers!$B$2:$B$1001,,0) -> Aloisia Allner | G3: =_xlfn.XLOOKUP(C3,customers!$A$2:$A$1001,customers!$G$2:$G$1001,,0) -> United States | H3: =INDEX(products!$A$1:$G$49,MATCH(orders!$D3,products!$A$1:$A$49,0),MATCH(orders!H$1,products!$A$1:$G$1,0)) -> Exc | I3: =INDEX(products!$A$1:$G$49,MATCH(orders!$D3,products!$A$1:$A$49,0),MATCH(orders!I$1,products!$A$1:$G$1,0)) -> M | J3: =INDEX(products!$A$1:$G$49,MATCH(orders!$D3,products!$A$1:$A$49,0),MATCH(orders!J$1,products!$A$1:$G$1,0)) -> 0.5 | K3: =INDEX(products!$A$1:$G$49,MATCH(orders!$D3,products!$A$1:$A$49,0),MATCH(orders!K$1,products!$A$1:$G$1,0)) -> 8.25 | L3: =K3*E3 -> 41.25 | M3: {=_xlfn.IFS(H3="Rob","Robusta",H3="Exc","Excelsa",H3="Ara","Arabica",H3="Lib","Liberica")} -> Excelsa | N3: {=_xlfn.IFS(I3="M","Medium",I3="L","Light",I3="D","Dark")} -> Medium | O3: =_xlfn.XLOOKUP(Orders[[#This Row],[Customer ID]],customers!$A$2:$A$1001,customers!$I$2:$I$1001,,0) -> Yes
A4: FAA-43335-268 | B4: 44364 | C4: 21125-22134-PX | D4: A-L-1 | E4: 1 | F4: =_xlfn.XLOOKUP(C4,customers!$A$2:$A$1001,customers!$B$2:$B$1001,,0) -> Jami Redholes | G4: =_xlfn.XLOOKUP(C4,customers!$A$2:$A$1001,customers!$G$2:$G$1001,,0) -> United States | H4: =INDEX(products!$A$1:$G$49,MATCH(orders!$D4,products!$A$1:$A$49,0),MATCH(orders!H$1,products!$A$1:$G$1,0)) -> Ara | I4: =INDEX(products!$A$1:$G$49,MATCH(orders!$D4,products!$A$1:$A$49,0),MATCH(orders!I$1,products!$A$1:$G$1,0)) -> L | J4: =INDEX(products!$A$1:$G$49,MATCH(orders!$D4,products!$A$1:$A$49,0),MATCH(orders!J$1,products!$A$1:$G$1,0)) -> 1 | K4: =INDEX(products!$A$1:$G$49,MATCH(orders!$D4,products!$A$1:$A$49,0),MATCH(orders!K$1,products!$A$1:$G$1,0)) -> 12.95 | L4: =K4*E4 -> 12.95 | M4: {=_xlfn.IFS(H4="Rob","Robusta",H4="Exc","Excelsa",H4="Ara","Arabica",H4="Lib","Liberica")} -> Arabica | N4: {=_xlfn.IFS(I4="M","Medium",I4="L","Light",I4="D","Dark")} -> Light | O4: =_xlfn.XLOOKUP(Orders[[#This Row],[Customer ID]],customers!$A$2:$A$1001,customers!$I$2:$I$1001,,0) -> Yes
A5: KAC-83089-793 | B5: 44392 | C5: 23806-46781-OU | D5: E-M-1 | E5: 2 | F5: =_xlfn.XLOOKUP(C5,customers!$A$2:$A$1001,customers!$B$2:$B$1001,,0) -> Christoffer O' Shea | G5: =_xlfn.XLOOKUP(C5,customers!$A$2:$A$1001,customers!$G$2:$G$1001,,0) -> Ireland | H5: =INDEX(products!$A$1:$G$49,MATCH(orders!$D5,products!$A$1:$A$49,0),MATCH(orders!H$1,products!$A$1:$G$1,0)) -> Exc | I5: =INDEX(products!$A$1:$G$49,MATCH(orders!$D5,products!$A$1:$A$49,0),MATCH(orders!I$1,products!$A$1:$G$1,0)) -> M | J5: =INDEX(products!$A$1:$G$49,MATCH(orders!$D5,products!$A$1:$A$49,0),MATCH(orders!J$1,products!$A$1:$G$1,0)) -> 1 | K5: =INDEX(products!$A$1:$G$49,MATCH(orders!$D5,products!$A$1:$A$49,0),MATCH(orders!K$1,products!$A$1:$G$1,0)) -> 13.75 | L5: =K5*E5 -> 27.5 | M5: {=_xlfn.IFS(H5="Rob","Robusta",H5="Exc","Excelsa",H5="Ara","Arabica",H5="Lib","Liberica")} -> Excelsa | N5: {=_xlfn.IFS(I5="M","Medium",I5="L","Light",I5="D","Dark")} -> Medium | O5: =_xlfn.XLOOKUP(Orders[[#This Row],[Customer ID]],customers!$A$2:$A$1001,customers!$I$2:$I$1001,,0) -> No
A6: KAC-83089-793 | B6: 44392 | C6: 23806-46781-OU | D6: R-L-2.5 | E6: 2 | F6: =_xlfn.XLOOKUP(C6,customers!$A$2:$A$1001,customers!$B$2:$B$1001,,0) -> Christoffer O' Shea | G6: =_xlfn.XLOOKUP(C6,customers!$A$2:$A$1001,customers!$G$2:$G$1001,,0) -> Ireland | H6: =INDEX(products!$A$1:$G$49,MATCH(orders!$D6,products!$A$1:$A$49,0),MATCH(orders!H$1,products!$A$1:$G$1,0)) -> Rob | I6: =INDEX(products!$A$1:$G$49,MATCH(orders!$D6,products!$A$1:$A$49,0),MATCH(orders!I$1,products!$A$1:$G$1,0)) -> L | J6: =INDEX(products!$A$1:$G$49,MATCH(orders!$D6,products!$A$1:$A$49,0),MATCH(orders!J$1,products!$A$1:$G$1,0)) -> 2.5 | K6: =INDEX(products!$A$1:$G$49,MATCH(orders!$D6,products!$A$1:$A$49,0),MATCH(orders!K$1,products!$A$1:$G$1,0)) -> 27.485 | L6: =K6*E6 -> 54.97 | M6: {=_xlfn.IFS(H6="Rob","Robusta",H6="Exc","Excelsa",H6="Ara","Arabica",H6="Lib","Liberica")} -> Robusta | N6: {=_xlfn.IFS(I6="M","Medium",I6="L","Light",I6="D","Dark")} -> Light | O6: =_xlfn.XLOOKUP(Orders[[#This Row],[Customer ID]],customers!$A$2:$A$1001,customers!$I$2:$I$1001,,0) -> No
A7: CVP-18956-553 | B7: 44412 | C7: 86561-91660-RB | D7: L-D-1 | E7: 3 | F7: =_xlfn.XLOOKUP(C7,customers!$A$2:$A$1001,customers!$B$2:$B$1001,,0) -> Beryle Cottier | G7: =_xlfn.XLOOKUP(C7,customers!$A$2:$A$1001,customers!$G$2:$G$1001,,0) -> United States | H7: =INDEX(products!$A$1:$G$49,MATCH(orders!$D7,products!$A$1:$A$49,0),MATCH(orders!H$1,products!$A$1:$G$1,0)) -> Lib | I7: =INDEX(products!$A$1:$G$49,MATCH(orders!$D7,products!$A$1:$A$49,0),MATCH(orders!I$1,products!$A$1:$G$1,0)) -> D | J7: =INDEX(products!$A$1:$G$49,MATCH(orders!$D7,products!$A$1:$A$49,0),MATCH(orders!J$1,products!$A$1:$G$1,0)) -> 1 | K7: =INDEX(products!$A$1:$G$49,MATCH(orders!$D7,products!$A$1:$A$49,0),MATCH(orders!K$1,products!$A$1:$G$1,0)) -> 12.95 | L7: =K7*E7 -> 38.85 | M7: {=_xlfn.IFS(H7="Rob","Robusta",H7="Exc","Excelsa",H7="Ara","Arabica",H7="Lib","Liberica")} -> Liberica | N7: {=_xlfn.IFS(I7="M","Medium",I7="L","Light",I7="D","Dark")} -> Dark | O7: =_xlfn.XLOOKUP(Orders[[#This Row],[Customer ID]],customers!$A$2:$A$1001,customers!$I$2:$I$1001,,0) -> No
A8: IPP-31994-879 | B8: 44582 | C8: 65223-29612-CB | D8: E-D-0.5 | E8: 3 | F8: =_xlfn.XLOOKUP(C8,customers!$A$2:$A$1001,customers!$B$2:$B$1001,,0) -> Shaylynn Lobe | G8: =_xlfn.XLOOKUP(C8,customers!$A$2:$A$1001,customers!$G$2:$G$1001,,0) -> United States | H8: =INDEX(products!$A$1:$G$49,MATCH(orders!$D8,products!$A$1:$A$49,0),MATCH(orders!H$1,products!$A$1:$G$1,0)) -> Exc | I8: =INDEX(products!$A$1:$G$49,MATCH(orders!$D8,products!$A$1:$A$49,0),MATCH(orders!I$1,products!$A$1:$G$1,0)) -> D | J8: =INDEX(products!$A$1:$G$49,MATCH(orders!$D8,products!$A$1:$A$49,0),MATCH(orders!J$1,products!$A$1:$G$1,0)) -> 0.5 | K8: =INDEX(products!$A$1:$G$49,MATCH(orders!$D8,products!$A$1:$A$49,0),MATCH(orders!K$1,products!$A$1:$G$1,0)) -> 7.29 | L8: =K8*E8 -> 21.87 | M8: {=_xlfn.IFS(H8="Rob","Robusta",H8="Exc","Excelsa",H8="Ara","Arabica",H8="Lib","Liberica")} -> Excelsa | N8: {=_xlfn.IFS(I8="M","Medium",I8="L","Light",I8="D","Dark")} -> Dark | O8: =_xlfn.XLOOKUP(Orders[[#This Row],[Customer ID]],customers!$A$2:$A$1001,customers!$I$2:$I$1001,,0) -> Yes
A9: SNZ-65340-705 | B9: 44701 | C9: 21134-81676-FR | D9: L-L-0.2 | E9: 1 | F9: =_xlfn.XLOOKUP(C9,customers!$A$2:$A$1001,customers!$B$2:$B$1001,,0) -> Melvin Wharfe | G9: =_xlfn.XLOOKUP(C9,customers!$A$2:$A$1001,customers!$G$2:$G$1001,,0) -> Ireland | H9: =INDEX(products!$A$1:$G$49,MATCH(orders!$D9,products!$A$1:$A$49,0),MATCH(orders!H$1,products!$A$1:$G$1,0)) -> Lib | I9: =INDEX(products!$A$1:$G$49,MATCH(orders!$D9,products!$A$1:$A$49,0),MATCH(orders!I$1,products!$A$1:$G$1,0)) -> L | J9: =INDEX(products!$A$1:$G$49,MATCH(orders!$D9,products!$A$1:$A$49,0),MATCH(orders!J$1,products!$A$1:$G$1,0)) -> 0.2 | K9: =INDEX(products!$A$1:$G$49,MATCH(orders!$D9,products!$A$1:$A$49,0),MATCH(orders!K$1,products!$A$1:$G$1,0)) -> 4.755 | L9: =K9*E9 -> 4.755 | M9: {=_xlfn.IFS(H9="Rob","Robusta",H9="Exc","Excelsa",H9="Ara","Arabica",H9="Lib","Liberica")} -> Liberica | N9: {=_xlfn.IFS(I9="M","Medium",I9="L","Light",I9="D","Dark")} -> Light | O9: =_xlfn.XLOOKUP(Orders[[#This Row],[Customer ID]],customers!$A$2:$A$1001,customers!$I$2:$I$1001,,0) -> Yes
A10: EZT-46571-659 | B10: 43467 | C10: 03396-68805-ZC | D10: R-M-0.5 | E10: 3 | F10: =_xlfn.XLOOKUP(C10,customers!$A$2:$A$1001,customers!$B$2:$B$1001,,0) -> Guthrey Petracci | G10: =_xlfn.XLOOKUP(C10,customers!$A$2:$A$1001,customers!$G$2:$G$1001,,0) -> United States | H10: =INDEX(products!$A$1:$G$49,MATCH(orders!$D10,products!$A$1:$A$49,0),MATCH(orders!H$1,products!$A$1:$G$1,0)) -> Rob | I10: =INDEX(products!$A$1:$G$49,MATCH(orders!$D10,products!$A$1:$A$49,0),MATCH(orders!I$1,products!$A$1:$G$1,0)) -> M | J10: =INDEX(products!$A$1:$G$49,MATCH(orders!$D10,products!$A$1:$A$49,0),MATCH(orders!J$1,products!$A$1:$G$1,0)) -> 0.5 | K10: =INDEX(products!$A$1:$G$49,MATCH(orders!$D10,products!$A$1:$A$49,0),MATCH(orders!K$1,products!$A$1:$G$1,0)) -> 5.97 | L10: =K10*E10 -> 17.91 | M10: {=_xlfn.IFS(H10="Rob","Robusta",H10="Exc","Excelsa",H10="Ara","Arabica",H10="Lib","Liberica")} -> Robusta | N10: {=_xlfn.IFS(I10="M","Medium",I10="L","Light",I10="D","Dark")} -> Medium | O10: =_xlfn.XLOOKUP(Orders[[#This Row],[Customer ID]],customers!$A$2:$A$1001,customers!$I$2:$I$1001,,0) -> No
A11: NWQ-70061-912 | B11: 43713 | C11: 61021-27840-ZN | D11: R-M-0.5 | E11: 1 | F11: =_xlfn.XLOOKUP(C11,customers!$A$2:$A$1001,customers!$B$2:$B$1001,,0) -> Rodger Raven | G11: =_xlfn.XLOOKUP(C11,customers!$A$2:$A$1001,customers!$G$2:$G$1001,,0) -> United States | H11: =INDEX(products!$A$1:$G$49,MATCH(orders!$D11,products!$A$1:$A$49,0),MATCH(orders!H$1,products!$A$1:$G$1,0)) -> Rob | I11: =INDEX(products!$A$1:$G$49,MATCH(orders!$D11,products!$A$1:$A$49,0),MATCH(orders!I$1,products!$A$1:$G$1,0)) -> M | J11: =INDEX(products!$A$1:$G$49,MATCH(orders!$D11,products!$A$1:$A$49,0),MATCH(orders!J$1,products!$A$1:$G$1,0)) -> 0.5 | K11: =INDEX(products!$A$1:$G$49,MATCH(orders!$D11,products!$A$1:$A$49,0),MATCH(orders!K$1,products!$A$1:$G$1,0)) -> 5.97 | L11: =K11*E11 -> 5.97 | M11: {=_xlfn.IFS(H11="Rob","Robusta",H11="Exc","Excelsa",H11="Ara","Arabica",H11="Lib","Liberica")} -> Robusta | N11: {=_xlfn.IFS(I11="M","Medium",I11="L","Light",I11="D","Dark")} -> Medium | O11: =_xlfn.XLOOKUP(Orders[[#This Row],[Customer ID]],customers!$A$2:$A$1001,customers!$I$2:$I$1001,,0) -> No
A12: BKK-47233-845 | B12: 44263 | C12: 76239-90137-UQ | D12: A-D-1 | E12: 4 | F12: =_xlfn.XLOOKUP(C12,customers!$A$2:$A$1001,customers!$B$2:$B$1001,,0) -> Ferrell Ferber | G12: =_xlfn.XLOOKUP(C12,customers!$A$2:$A$1001,customers!$G$2:$G$1001,,0) -> United States | H12: =INDEX(products!$A$1:$G$49,MATCH(orders!$D12,products!$A$1:$A$49,0),MATCH(orders!H$1,products!$A$1:$G$1,0)) -> Ara | I12: =INDEX(products!$A$1:$G$49,MATCH(orders!$D12,products!$A$1:$A$49,0),MATCH(orders!I$1,products!$A$1:$G$1,0)) -> D | J12: =INDEX(products!$A$1:$G$49,MATCH(orders!$D12,products!$A$1:$A$49,0),MATCH(orders!J$1,products!$A$1:$G$1,0)) -> 1 | K12: =INDEX(products!$A$1:$G$49,MATCH(orders!$D12,products!$A$1:$A$49,0),MATCH(orders!K$1,products!$A$1:$G$1,0)) -> 9.95 | L12: =K12*E12 -> 39.8 | M12: {=_xlfn.IFS(H12="Rob","Robusta",H12="Exc","Excelsa",H12="Ara","Arabica",H12="Lib","Liberica")} -> Arabica | N12: {=_xlfn.IFS(I12="M","Medium",I12="L","Light",I12="D","Dark")} -> Dark | O12: =_xlfn.XLOOKUP(Orders[[#This Row],[Customer ID]],customers!$A$2:$A$1001,customers!$I$2:$I$1001,,0) -> No
A13: VQR-01002-970 | B13: 44132 | C13: 49315-21985-BB | D13: E-L-2.5 | E13: 5 | F13: =_xlfn.XLOOKUP(C13,customers!$A$2:$A$1001,customers!$B$2:$B$1001,,0) -> Duky Phizackerly | G13: =_xlfn.XLOOKUP(C13,customers!$A$2:$A$1001,customers!$G$2:$G$1001,,0) -> United States | H13: =INDEX(products!$A$1:$G$49,MATCH(orders!$D13,products!$A$1:$A$49,0),MATCH(orders!H$1,products!$A$1:$G$1,0)) -> Exc | I13: =INDEX(products!$A$1:$G$49,MATCH(orders!$D13,products!$A$1:$A$49,0),MATCH(orders!I$1,products!$A$1:$G$1,0)) -> L | J13: =INDEX(products!$A$1:$G$49,MATCH(orders!$D13,products!$A$1:$A$49,0),MATCH(orders!J$1,products!$A$1:$G$1,0)) -> 2.5 | K13: =INDEX(products!$A$1:$G$49,MATCH(orders!$D13,products!$A$1:$A$49,0),MATCH(orders!K$1,products!$A$1:$G$1,0)) -> 34.155 | L13: =K13*E13 -> 170.775 | M13: {=_xlfn.IFS(H13="Rob","Robusta",H13="Exc","Excelsa",H13="Ara","Arabica",H13="Lib","Liberica")} -> Excelsa | N13: {=_xlfn.IFS(I13="M","Medium",I13="L","Light",I13="D","Dark")} -> Light | O13: =_xlfn.XLOOKUP(Orders[[#This Row],[Customer ID]],customers!$A$2:$A$1001,customers!$I$2:$I$1001,,0) -> Yes
... A1001: IRV-20769-219 | B1001: 44119 | C1001: 77131-58092-GE | D1001: E-M-0.2 | E1001: 3 | F1001: =_xlfn.XLOOKUP(C1001,customers!$A$2:$A$1001,customers!$B$2:$B$1001,,0) -> Vidovic Antonelli | G1001: =_xlfn.XLOOKUP(C1001,customers!$A$2:$A$1001,customers!$G$2:$G$1001,,0) -> United Kingdom | H1001: =INDEX(products!$A$1:$G$49,MATCH(orders!$D1001,products!$A$1:$A$49,0),MATCH(orders!H$1,products!$A$1:$G$1,0)) -> Exc | I1001: =INDEX(products!$A$1:$G$49,MATCH(orders!$D1001,products!$A$1:$A$49,0),MATCH(orders!I$1,products!$A$1:$G$1,0)) -> M | J1001: =INDEX(products!$A$1:$G$49,MATCH(orders!$D1001,products!$A$1:$A$49,0),MATCH(orders!J$1,products!$A$1:$G$1,0)) -> 0.2 | K1001: =INDEX(products!$A$1:$G$49,MATCH(orders!$D1001,products!$A$1:$A$49,0),MATCH(orders!K$1,products!$A$1:$G$1,0)) -> 4.125 | L1001: =K1001*E1001 -> 12.375 | M1001: {=_xlfn.IFS(H1001="Rob","Robusta",H1001="Exc","Excelsa",H1001="Ara","Arabica",H1001="Lib","Liberica")} -> Excelsa | N1001: {=_xlfn.IFS(I1001="M","Medium",I1001="L","Light",I1001="D","Dark")} -> Medium | O1001: =_xlfn.XLOOKUP(Orders[[#This Row],[Customer ID]],customers!$A$2:$A$1001,customers!$I$2:$I$1001,,0) -> Yes

Sheet customers
A1: Customer ID | B1: Customer Name | C1: Email | D1: Phone Number | E1: Address Line 1 | F1: City | G1: Country | H1: Postcode | I1: Loyalty Card
A2: 17670-51384-MA | B2: Aloisia Allner | C2: aallner0@lulu.com | D2: +1 (862) 817-0124 | E2: 57999 Pepper Wood Alley | F2: Paterson | G2: United States | H2: 7505 | I2: Yes
A3: 73342-18763-UW | B3: Piotr Bote | C3: pbote1@yelp.com | D3: +353 (913) 396-4653 | E3: 2112 Ridgeway Hill | F3: Crumlin | G3: Ireland | H3: D6W | I3: No
A4: 21125-22134-PX | B4: Jami Redholes | C4: jredholes2@tmall.com | D4: +1 (210) 986-6806 | E4: 5214 Bartillon Park | F4: San Antonio | G4: United States | H4: 78205 | I4: Yes
A5: 71253-00052-RN | B5: Dene Azema | C5: dazema3@facebook.com | D5: +1 (217) 418-0714 | E5: 27 Maywood Place | F5: Springfield | G5: United States | H5: 62711 | I5: Yes
A6: 23806-46781-OU | B6: Christoffer O' Shea | D6: +353 (698) 362-9201 | E6: 38980 Manitowish Junction | F6: Cill Airne | G6: Ireland | H6: N41 | I6: No
A7: 86561-91660-RB | B7: Beryle Cottier | D7: +1 (570) 289-7473 | E7: 2651 Stoughton Place | F7: Scranton | G7: United States | H7: 18505 | I7: No
A8: 65223-29612-CB | B8: Shaylynn Lobe | C8: slobe6@nifty.com | D8: +1 (937) 954-4541 | E8: 7005 Mariners Cove Place | F8: Dayton | G8: United States | H8: 45440 | I8: Yes
A9: 21134-81676-FR | B9: Melvin Wharfe | D9: +353 (507) 574-3034 | E9: 7 Straubel Road | F9: Kill | G9: Ireland | H9: P24 | I9: Yes
A10: 03396-68805-ZC | B10: Guthrey Petracci | C10: gpetracci8@livejournal.com | D10: +1 (310) 868-1842 | E10: 949 Paget Parkway | F10: Los Angeles | G10: United States | H10: 90045 | I10: No
A11: 61021-27840-ZN | B11: Rodger Raven | C11: rraven9@ed.gov | D11: +1 (213) 263-0288 | E11: 1 Reinke Avenue | F11: Los Angeles | G11: United States | H11: 90065 | I11: No
A12: 76239-90137-UQ | B12: Ferrell Ferber | C12: fferbera@businesswire.com | D12: +1 (408) 383-5302 | E12: 68 High Crossing Court | F12: San Jose | G12: United States | H12: 95160 | I12: No
A13: 49315-21985-BB | B13: Duky Phizackerly | C13: dphizackerlyb@utexas.edu | D13: +1 (408) 533-6012 | E13: 28643 Bluejay Crossing | F13: San Jose | G13: United States | H13: 95194 | I13: Yes
A14: 34136-36674-OM | B14: Rosaleen Scholar | C14: rscholarc@nyu.edu | D14: +1 (804) 420-0420 | E14: 80915 Montana Park | F14: Richmond | G14: United States | H14: 23285 | I14: No
A15: 39396-12890-PE | B15: Terence Vanyutin | C15: tvanyutind@wix.com | E15: 331 Bunting Hill | F15: Migrate | G15: United States | H15: 41905 | I15: No
A16: 95875-73336-RG | B16: Patrice Trobe | C16: ptrobee@wunderground.com | D16: +1 (314) 240-7896 | E16: 827 Declaration Plaza | F16: Saint Louis | G16: United States | H16: 63131 | I16: Yes
A17: 25473-43727-BY | B17: Llywellyn Oscroft | C17: loscroftf@ebay.co.uk | E17: 022 Roth Place | F17: Philadelphia | G17: United States | H17: 19172 | I17: No
A18: 99643-51048-IQ | B18: Minni Alabaster | C18: malabasterg@hexun.com | D18: +1 (971) 483-6255 | E18: 3 Charing Cross Trail | F18: Portland | G18: United States | H18: 97271 | I18: No
A19: 62173-15287-CU | B19: Rhianon Broxup | C19: rbroxuph@jimdo.com | D19: +1 (713) 663-1338 | E19: 83517 Thierer Court | F19: Houston | G19: United States | H19: 77240 | I19: No
A20: 57611-05522-ST | B20: Pall Redford | C20: predfordi@ow.ly | E20: 7337 Hayes Junction | F20: Caherconlish | G20: Ireland | H20: F45 | I20: Yes
A21: 76664-37050-DT | B21: Aurea Corradino | C21: acorradinoj@harvard.edu | D21: +1 (646) 202-5965 | E21: 698 Canary Terrace | F21: New York City | G21: United States | H21: 10060 | I21: Yes
A22: 84565-53984-SX | B22: Kendal Scardefield | D22: +353 (733) 405-3302 | E22: 3 Northridge Crossing | F22: Clondalkin | G22: Ireland | H22: D24 | I22: Yes
A23: 03090-88267-BQ | B23: Avrit Davidowsky | C23: adavidowskyl@netvibes.com | D23: +1 (616) 481-9962 | E23: 9 Warrior Junction | F23: Grand Rapids | G23: United States | H23: 49560 | I23: No
A24: 37651-47492-NC | B24: Annabel Antuk | C24: aantukm@kickstarter.com | D24: +1 (941) 740-6268 | E24: 77965 Lawn Park | F24: Punta Gorda | G24: United States | H24: 33982 | I24: Yes
A25: 95399-57205-HI | B25: Iorgo Kleinert | C25: ikleinertn@timesonline.co.uk | D25: +1 (360) 352-6598 | E25: 1 Morningstar Lane | F25: Vancouver | G25: United States | H25: 98682 | I25: Yes
A26: 24010-66714-HW | B26: Chrisy Blofeld | C26: cblofeldo@amazon.co.uk | D26: +1 (303) 936-3357 | E26: 013 Talisman Terrace | F26: Englewood | G26: United States | H26: 80150 | I26: No
A27: 07591-92789-UA | B27: Culley Farris | D27: +1 (941) 267-4822 | E27: 4 Mitchell Drive | F27: Punta Gorda | G27: United States | H27: 33982 | I27: Yes
A28: 49231-44455-IC | B28: Selene Shales | C28: sshalesq@umich.edu | D28: +1 (707) 881-5004 | E28: 74 Bultman Plaza | F28: Petaluma | G28: United States | H28: 94975 | I28: Yes
A29: 50124-88608-EO | B29: Vivie Danneil | C29: vdanneilr@mtv.com | D29: +353 (751) 346-0399 | E29: 5626 Darwin Avenue | F29: Tralee | G29: Ireland | H29: V92 | I29: No
A30: 00888-74814-UZ | B30: Theresita Newbury | C30: tnewburys@usda.gov | D30: +353 (803) 587-0026 | E30: 79526 Bultman Lane | F30: Clonskeagh | G30: Ireland | H30: D04 | I30: No
A31: 14158-30713-OB | B31: Mozelle Calcutt | C31: mcalcuttt@baidu.com | D31: +353 (928) 869-1762 | E31: 4389 Russell Way | F31: Rathwire | G31: Ireland | H31: Y25 | I31: Yes
A32: 51427-89175-QJ | B32: Adrian Swaine | D32: +1 (303) 486-9517 | E32: 95 Straubel Hill | F32: Aurora | G32: United States | H32: 80044 | I32: No
A33: 52082-49024-ON | B33: Ray Leivesley | C33: rleivesleyv@canalblog.com | D33: +1 (212) 535-7791 | E33: 91 Stephen Drive | F33: Jamaica | G33: United States | H33: 11407 | I33: No
A34: 04540-43685-DV | B34: Nelly Basezzi | C34: nbasezziw@webeden.co.uk | D34: +353 (125) 815-7345 | E34: 923 Mallard Junction | F34: Bailieborough | G34: Ireland | H34: C15 | I34: Yes
A35: 39123-12846-YJ | B35: Gallard Gatheral | C35: ggatheralx@123-reg.co.uk | E35: 40 Clemons Place | F35: Grand Forks | G35: United States | H35: 58207 | I35: No
A36: 44981-99666-XB | B36: Una Welberry | C36: uwelberryy@ebay.co.uk | D36: +44 (392) 503-8132 | E36: 40915 Schlimgen Park | F36: Upton | G36: United Kingdom | H36: DN21 | I36: Yes
A37: 24825-51803-CQ | B37: Faber Eilhart | C37: feilhartz@who.int | D37: +1 (304) 510-6095 | E37: 6966 Victoria Street | F37: Charleston | G37: United States | H37: 25362 | I37: No
A38: 77634-13918-GJ | B38: Zorina Ponting | C38: zponting10@altervista.org | D38: +1 (501) 172-1476 | E38: 7118 Holmberg Court | F38: Little Rock | G38: United States | H38: 72204 | I38: No
A39: 13694-25001-LX | B39: Silvio Strase | C39: sstrase11@booking.com | D39: +1 (303) 579-8015 | E39: 5 Forest Lane | F39: Denver | G39: United States | H39: 80291 | I39: No
A40: 08523-01791-TI | B40: Dorie de la Tremoille | C40: dde12@unesco.org | D40: +1 (612) 492-5160 | E40: 0817 Dennis Street | F40: Minneapolis | G40: United States | H40: 55458 | I40: No
A41: 49860-68865-AB | B41: Hy Zanetto | E41: 469 Paget Place | F41: Tucson | G41: United States | H41: 85715 | I41: Yes
A42: 21240-83132-SP | B42: Jessica McNess | D42: +1 (504) 545-1478 | E42: 664 Erie Place | F42: New Orleans | G42: United States | H42: 70116 | I42: No
A43: 08350-81623-TF | B43: Lorenzo Yeoland | C43: lyeoland15@pbs.org | D43: +1 (860) 576-2887 | E43: 8510 Merrick Road | F43: Hartford | G43: United States | H43: 6183 | I43: Yes
A44: 73284-01385-SJ | B44: Abigail Tolworthy | C44: atolworthy16@toplist.cz | D44: +1 (801) 722-4425 | E44: 74 Shopko Way | F44: Ogden | G44: United States | H44: 84409 | I44: Yes
A45: 04152-34436-IE | B45: Maurie Bartol | D45: +1 (617) 493-7594 | E45: 7625 Starling Court | F45: Boston | G45: United States | H45: 2216 | I45: No
A46: 06631-86965-XP | B46: Olag Baudassi | C46: obaudassi18@seesaa.net | D46: +1 (585) 356-6251 | E46: 55 Dottie Court | F46: Rochester | G46: United States | H46: 14604 | I46: Yes
A47: 54619-08558-ZU | B47: Petey Kingsbury | C47: pkingsbury19@comcast.net | D47: +1 (917) 705-8224 | E47: 28 Loftsgordon Place | F47: Bronx | G47: United States | H47: 10469 | I47: No
A48: 85589-17020-CX | B48: Donna Baskeyfied | D48: +1 (205) 923-1460 | E48: 7586 Logan Avenue | F48: Birmingham | G48: United States | H48: 35205 | I48: Yes
A49: 36078-91009-WU | B49: Arda Curley | C49: acurley1b@hao123.com | D49: +1 (760) 840-3808 | E49: 45098 Scott Drive | F49: San Bernardino | G49: United States | H49: 92415 | I49: Yes
A50: 15770-27099-GX | B50: Raynor McGilvary | C50: rmcgilvary1c@tamu.edu | E50: 496 Rockefeller Court | F50: Norfolk | G50: United States | H50: 23514 | I50: No
A51: 91460-04823-BX | B51: Isis Pikett | C51: ipikett1d@xinhuanet.com | D51: +1 (202) 871-9039 | E51: 5892 Hauk Drive | F51: Washington | G51: United States | H51: 20409 | I51: No
A52: 45089-52817-WN | B52: Inger Bouldon | C52: ibouldon1e@gizmodo.com | D52: +1 (754) 391-4736 | E52: 925 Barby Circle | F52: Fort Lauderdale | G52: United States | H52: 33355 | I52: No
A53: 76447-50326-IC | B53: Karry Flanders | C53: kflanders1f@over-blog.com | D53: +353 (467) 720-7274 | E53: 88 Blue Bill Park Avenue | F53: Crumlin | G53: Ireland | H53: D6W | I53: Yes
A54: 26333-67911-OL | B54: Hartley Mattioli | C54: hmattioli1g@webmd.com | E54: 126 Valley Edge Street | F54: Kinloch | G54: United Kingdom | H54: PH43 | I54: No
A55: 40768-49176-BL | B55: Horatio Rubberts | C55: hrubberts1h@google.com.hk | D55: +1 (801) 635-8791 | E55: 459 Russell Center | F55: Provo | G55: United States | H55: 84605 | I55: No
A56: 22107-86640-SB | B56: Archambault Gillard | C56: agillard1i@issuu.com | D56: +1 (419) 663-2236 | E56: 97490 Susan Avenue | F56: Toledo | G56: United States | H56: 43666 | I56: No
A57: 09960-34242-LZ | B57: Salomo Cushworth | D57: +1 (609) 409-7044 | E57: 44 Oneill Parkway | F57: Trenton | G57: United States | H57: 8650 | I57: No
A58: 04671-85591-RT | B58: Theda Grizard | C58: tgrizard1k@odnoklassniki.ru | D58: +1 (813) 243-2150 | E58: 6 Knutson Pass | F58: Tampa | G58: United States | H58: 33686 | I58: Yes
A59: 25729-68859-UA | B59: Rozele Relton | C59: rrelton1l@stanford.edu | D59: +1 (850) 626-1181 | E59: 2484 Reindahl Court | F59: Pensacola | G59: United States | H59: 32590 | I59: No
A60: 05501-86351-NX | B60: Willa Rolling | D60: +1 (813) 759-3534 | E60: 3 Mockingbird Plaza | F60: Zephyrhills | G60: United States | H60: 33543 | I60: Yes
A61: 04521-04300-OK | B61: Stanislaus Gilroy | C61: sgilroy1n@eepurl.com | E61: 9120 Harbort Terrace | F61: Saint Paul | G61: United States | H61: 55123 | I61: Yes
A62: 58689-55264-VK | B62: Correy Cottingham | C62: ccottingham1o@wikipedia.org | D62: +1 (260) 764-1820 | E62: 394 Logan Road | F62: Fort Wayne | G62: United States | H62: 46862 | I62: No
A63: 79436-73011-MM | B63: Pammi Endacott | D63: +44 (177) 260-5076 | E63: 5841 Atwood Lane | F63: Wootton | G63: United Kingdom | H63: NN4 | I63: Yes
A64: 65552-60476-KY | B64: Nona Linklater | D64: +1 (239) 347-9766 | E64: 856 Bonner Parkway | F64: Naples | G64: United States | H64: 34114 | I64: Yes
A65: 69904-02729-YS | B65: Annadiane Dykes | C65: adykes1r@eventbrite.com | D65: +1 (312) 111-6203 | E65: 31 Northport Terrace | F65: Chicago | G65: United States | H65: 60681 | I65: No
A66: 01433-04270-AX | B66: Felecia Dodgson | D66: +1 (973) 434-8662 | E66: 48053 8th Crossing | F66: Newark | G66: United States | H66: 7104 | I66: Yes
A67: 14204-14186-LA | B67: Angelia Cockrem | C67: acockrem1t@engadget.com | D67: +1 (571) 316-8217 | E67: 1 Sherman Alley | F67: Vienna | G67: United States | H67: 22184 | I67: Yes
A68: 32948-34398-HC | B68: Belvia Umpleby | C68: bumpleby1u@soundcloud.com | D68: +1 (682) 627-0888 | E68: 710 Prairie Rose Terrace | F68: Fort Worth | G68: United States | H68: 76178 | I68: Yes
A69: 77343-52608-FF | B69: Nat Saleway | C69: nsaleway1v@dedecms.com | D69: +1 (323) 473-0294 | E69: 0780 Anthes Plaza | F69: Burbank | G69: United States | H69: 91505 | I69: No
A70: 42770-36274-QA | B70: Hayward Goulter | C70: hgoulter1w@abc.net.au | D70: +1 (423) 764-7751 | E70: 2081 Mariners Cove Drive | F70: Kingsport | G70: United States | H70: 37665 | I70: No
A71: 14103-58987-ZU | B71: Gay Rizzello | C71: grizzello1x@symantec.com | D71: +44 (247) 225-8003 | E71: 21 Schmedeman Crossing | F71: Liverpool | G71: United Kingdom | H71: L33 | I71: Yes
A72: 69958-32065-SW | B72: Shannon List | C72: slist1y@mapquest.com | D72: +1 (614) 279-9816 | E72: 7123 Algoma Center | F72: Columbus | G72: United States | H72: 43231 | I72: No
A73: 69533-84907-FA | B73: Shirlene Edmondson | C73: sedmondson1z@theguardian.com | D73: +353 (248) 428-7978 | E73: 4752 International Point | F73: Newmarket on Fergus | G73: Ireland | H73: P17 | I73: No
A74: 76005-95461-CI | B74: Aurlie McCarl | D74: +1 (504) 209-2724 | E74: 731 David Park | F74: New Orleans | G74: United States | H74: 70183 | I74: No
A75: 15395-90855-VB | B75: Alikee Carryer | D75: +1 (704) 799-5219 | E75: 247 Helena Drive | F75: Charlotte | G75: United States | H75: 28230 | I75: Yes
A76: 80640-45811-LB | B76: Jennifer Rangall | C76: jrangall22@newsvine.com | D76: +1 (781) 512-6637 | E76: 0 Grasskamp Lane | F76: Springfield | G76: United States | H76: 1114 | I76: Yes
A77: 28476-04082-GR | B77: Kipper Boorn | C77: kboorn23@ezinearticles.com | D77: +353 (359) 134-1550 | E77: 9513 Meadow Ridge Parkway | F77: Listowel | G77: Ireland | H77: V31 | I77: Yes
A78: 12018-75670-EU | B78: Melania Beadle | D78: +353 (569) 458-9673 | E78: 4418 Quincy Terrace | F78: Moycullen | G78: Ireland | H78: A41 | I78: Yes
A79: 86437-17399-FK | B79: Colene Elgey | C79: celgey25@webs.com | D79: +1 (432) 261-0702 | E79: 45 Marcy Crossing | F79: Midland | G79: United States | H79: 79705 | I79: No
A80: 62979-53167-ML | B80: Lothaire Mizzi | C80: lmizzi26@rakuten.co.jp | D80: +1 (214) 719-8530 | E80: 74 Atwood Lane | F80: Dallas | G80: United States | H80: 75323 | I80: Yes
A81: 54810-81899-HL | B81: Cletis Giacomazzo | C81: cgiacomazzo27@jigsy.com | D81: +1 (571) 703-2064 | E81: 817 Ridgeway Hill | F81: Dulles | G81: United States | H81: 20189 | I81: No
A82: 26103-41504-IB | B82: Ami Arnow | C82: aarnow28@arizona.edu | D82: +1 (650) 238-1964 | E82: 12 Oakridge Court | F82: Oakland | G82: United States | H82: 94627 | I82: Yes
A83: 76534-45229-SG | B83: Sheppard Yann | C83: syann29@senate.gov | D83: +1 (719) 803-5276 | E83: 4 Farmco Place | F83: Colorado Springs | G83: United States | H83: 80930 | I83: Yes
A84: 81744-27332-RR | B84: Bunny Naulls | C84: bnaulls2a@tiny.cc | D84: +353 (809) 128-0755 | E84: 595 Melby Avenue | F84: Adare | G84: Ireland | H84: H54 | I84: Yes
A85: 91513-75657-PH | B85: Hally Lorait | D85: +1 (716) 869-3749 | E85: 80 Jana Avenue | F85: Buffalo | G85: United States | H85: 14205 | I85: Yes
A86: 30373-66619-CB | B86: Zaccaria Sherewood | C86: zsherewood2c@apache.org | D86: +1 (209) 433-7924 | E86: 1325 Jay Terrace | F86: Fresno | G86: United States | H86: 93715 | I86: No
A87: 31582-23562-FM | B87: Jeffrey Dufaire | C87: jdufaire2d@fc2.com | E87: 8 Buell Junction | F87: Fort Worth | G87: United States | H87: 76121 | I87: No
A88: 58638-01029-CB | B88: Blancha McAmish | C88: bmcamish2e@tripadvisor.com | E88: 5484 Stephen Court | F88: Oklahoma City | G88: United States | H88: 73179 | I88: Yes
A89: 81431-12577-VD | B89: Beitris Keaveney | C89: bkeaveney2f@netlog.com | E89: 67319 Redwing Parkway | F89: Beaumont | G89: United States | H89: 77705 | I89: No
A90: 68894-91205-MP | B90: Elna Grise | C90: egrise2g@cargocollective.com | E90: 92 Becker Circle | F90: Reno | G90: United States | H90: 89519 | I90: No
A91: 87602-55754-VN | B91: Torie Gottelier | C91: tgottelier2h@vistaprint.com | D91: +1 (816) 743-8492 | E91: 426 Division Avenue | F91: Kansas City | G91: United States | H91: 64136 | I91: No
A92: 39181-35745-WH | B92: Loydie Langlais | D92: +353 (576) 222-5069 | E92: 290 Ilene Street | F92: Crumlin | G92: Ireland | H92: D6W | I92: Yes
A93: 30381-64762-NG | B93: Adham Greenhead | C93: agreenhead2j@dailymail.co.uk | D93: +1 (951) 797-0738 | E93: 0062 Spenser Place | F93: Corona | G93: United States | H93: 92878 | I93: No
A94: 17503-27693-ZH | B94: Hamish MacSherry | D94: +1 (512) 430-4374 | E94: 7 Brentwood Plaza | F94: Austin | G94: United States | H94: 78759 | I94: Yes
A95: 89442-35633-HJ | B95: Else Langcaster | C95: elangcaster2l@spotify.com | D95: +44 (547) 590-3103 | E95: 3658 Jenna Street | F95: Normanton | G95: United Kingdom | H95: LE15 | I95: Yes
A96: 13654-85265-IL | B96: Rudy Farquharson | E96: 30178 Claremont Road | F96: Charlesland | G96: Ireland | H96: A63 | I96: Yes
A97: 40946-22090-FP | B97: Norene Magauran | C97: nmagauran2n@51.la | E97: 567 Artisan Place | F97: Fresno | G97: United States | H97: 93762 | I97: No
A98: 29050-93691-TS | B98: Vicki Kirdsch | C98: vkirdsch2o@google.fr | E98: 0263 Golf Street | F98: Saint Louis | G98: United States | H98: 63150 | I98: No
A99: 64395-74865-WF | B99: Ilysa Whapple | C99: iwhapple2p@com.com | D99: +1 (559) 522-1152 | E99: 41598 Everett Drive | F99: Fresno | G99: United States | H99: 93726 | I99: No
A100: 81861-66046-SU | B100: Ruy Cancellieri | D100: +353 (338) 743-8327 | E100: 251 Welch Parkway | F100: Confey | G100: Ireland | H100: A86 | I100: No
...

Sheet products
A1: Product ID | B1: Coffee Type | C1: Roast Type | D1: Size | E1: Unit Price | F1: Price per 100g | G1: Profit
A2: A-L-0.2 | B2: Ara | C2: L | D2: 0.2 | E2: 3.885 | F2: 1.9425 | G2: 0.34965
A3: A-L-0.5 | B3: Ara | C3: L | D3: 0.5 | E3: 7.77 | F3: 1.554 | G3: 0.6993
A4: A-L-1 | B4: Ara | C4: L | D4: 1 | E4: 12.95 | F4: 1.295 | G4: 1.1655
A5: A-L-2.5 | B5: Ara | C5: L | D5: 2.5 | E5: 29.785 | F5: 1.1914 | G5: 2.68065
A6: A-M-0.2 | B6: Ara | C6: M | D6: 0.2 | E6: 3.375 | F6: 1.6875 | G6: 0.30375
A7: A-M-0.5 | B7: Ara | C7: M | D7: 0.5 | E7: 6.75 | F7: 1.35 | G7: 0.6075
A8: A-M-1 | B8: Ara | C8: M | D8: 1 | E8: 11.25 | F8: 1.125 | G8: 1.0125
A9: A-M-2.5 | B9: Ara | C9: M | D9: 2.5 | E9: 25.875 | F9: 1.035 | G9: 2.32875
A10: A-D-0.2 | B10: Ara | C10: D | D10: 0.2 | E10: 2.985 | F10: 1.4925 | G10: 0.26865
A11: A-D-0.5 | B11: Ara | C11: D | D11: 0.5 | E11: 5.97 | F11: 1.194 | G11: 0.5373
A12: A-D-1 | B12: Ara | C12: D | D12: 1 | E12: 9.95 | F12: 0.995 | G12: 0.8955
A13: A-D-2.5 | B13: Ara | C13: D | D13: 2.5 | E13: 22.885 | F13: 0.9154 | G13: 2.05965
... A49: E-D-2.5 | B49: Exc | C49: D | D49: 2.5 | E49: 27.945 | F49: 1.1178 | G49: 3.07395

Sheet USD_NGN Historical Data
A1: Date | B1: Price | C1: Open | D1: High | E1: Low | F1: Vol. | G1: Change %
A2: 43466 | B2: 307.5 | C2: 307.1 | D2: 307.5 | E2: 307.1 | G2: 0
A3: 43467 | B3: 307.2 | C3: 307.25 | D3: 307.3 | E3: 306.8 | G3: -0.0002
A4: 43468 | B4: 306.3 | C4: 315 | D4: 315 | E4: 306.3 | G4: -0.0001
A5: 43469 | B5: 305.95 | C5: 306.4 | D5: 314.75 | E5: 306.34 | G5: 0.0002
A6: 43470 | B6: 305.92 | C6: 306.45 | D6: 306.45 | E6: 306.38 | G6: -0.0001
A7: 43472 | B7: 305.9 | C7: 306.4 | D7: 307.2 | E7: 306.38 | G7: 0
A8: 43473 | B8: 305.8 | C8: 306.3 | D8: 307.2 | E8: 306.3 | G8: 0
A9: 43475 | B9: 306 | C9: 306.45 | D9: 306.725 | E9: 306.4 | G9: 0.0002
A10: 43476 | B10: 306 | C10: 306.5 | D10: 307.15 | E10: 306.475 | G10: 0
A11: 43479 | B11: 307.3 | C11: 307.38 | D11: 307.5 | E11: 307.3 | G11: -0.0003
A12: 43480 | B12: 307.3 | C12: 307.3 | D12: 307.5 | E12: 307.3 | G12: 0
A13: 43481 | B13: 307.35 | C13: 307.38 | D13: 307.4 | E13: 307.3 | G13: 0.0002
... A263: 43831 | B263: 306 | C263: 306.5 | D263: 306.725 | E263: 306.475 | G263: 0
A264: 43834 | B264: 360 | C264: 360.5 | D264: 361.25 | E264: 360.5 | F264: 0.01K | G264: 0
A265: 43835 | B265: 360 | C265: 360.5 | D265: 360.5 | E265: 360.5 | G265: 0
A266: 43836 | B266: 360 | C266: 360.5 | D266: 361.25 | E266: 360.5 | F266: 0.00K | G266: 0
A267: 43837 | B267: 360 | C267: 360.5 | D267: 360.5 | E267: 360.5 | G267: 0
A268: 43839 | B268: 380.7 | C268: 381.2 | D268: 381.35 | E268: 380.25 | F268: 0.01K | G268: 0
A269: 43840 | B269: 380.6 | C269: 381.1 | D269: 381.1 | E269: 381.1 | G269: 0
A270: 43842 | B270: 380.7 | C270: 381.2 | D270: 381.2 | E270: 381.2 | G270: 0
A271: 43843 | B271: 305.9 | C271: 306.4 | D271: 306.7 | E271: 306.4 | G271: 0
A272: 43844 | B272: 305.9 | C272: 306.4 | D272: 306.7 | E272: 306.4 | G272: 0
A273: 43845 | B273: 305.9 | C273: 306.4 | D273: 306.7 | E273: 306.4 | G273: 0
A274: 43846 | B274: 305.88 | C274: 306.4 | D274: 306.7 | E274: 306.38 | G274: -0.0001
A275: 43847 | B275: 305.88 | C275: 306.38 | D275: 306.7 | E275: 306.38 | G275: 0
A276: 43850 | B276: 305.95 | C276: 306.4 | D276: 306.7 | E276: 306.4 | G276: 0.0002
A277: 43851 | B277: 305.95 | C277: 306.45 | D277: 306.7 | E277: 306.4 | G277: 0
A278: 43852 | B278: 305.95 | C278: 306.45 | D278: 306.7 | E278: 306.4 | G278: 0
A279: 43853 | B279: 305.95 | C279: 306.45 | D279: 306.7 | E279: 306.4 | F279: 0.03K | G279: 0
A280: 43854 | B280: 305.95 | C280: 306.45 | D280: 306.7 | E280: 306.4 | F280: 0.02K | G280: 0
A281: 43857 | B281: 305.92 | C281: 306.45 | D281: 306.7 | E281: 306.41 | F281: 0.04K | G281: -0.0001
A282: 43858 | B282: 305.9 | C282: 306.42 | D282: 306.7 | E282: 306.4 | F282: 0.04K | G282: -0.0001
A283: 43859 | B283: 306 | C283: 306.4 | D283: 307.25 | E283: 306.4 | F283: 0.05K | G283: 0.0003
A284: 43860 | B284: 306 | C284: 306.7 | D284: 307.25 | E284: 305.55 | F284: 0.01K | G284: 0
A285: 43861 | B285: 306 | C285: 306.5 | D285: 307.25 | E285: 306.45 | F285: 0.01K | G285: 0
A286: 43862 | B286: 307 | C286: 306.5 | D286: 307.5 | E286: 306.45 | G286: 0.0033
A287: 43864 | B287: 305.95 | C287: 306.4 | D287: 306.7 | E287: 306.4 | F287: 0.02K | G287: 0.0002
A288: 43865 | B288: 360 | C288: 360.5 | D288: 361.25 | E288: 360.25 | F288: 0.01K | G288: 0
A289: 43867 | B289: 360 | C289: 360.5 | D289: 361.25 | E289: 360.5 | F289: 0.01K | G289: 0
A290: 43868 | B290: 360 | C290: 360.5 | D290: 360.5 | E290: 360.5 | G290: 0
A291: 43870 | B291: 380.7 | C291: 381.2 | D291: 381.35 | E291: 380.25 | F291: 0.01K | G291: 0
A292: 43871 | B292: 380.6 | C292: 381.1 | D292: 381.1 | E292: 381.1 | G292: 0
A293: 43872 | B293: 380.7 | C293: 381.2 | D293: 381.35 | E293: 380.25 | F293: 0.01K | G293: 0
A294: 43873 | B294: 380.7 | C294: 381.2 | D294: 381.35 | E294: 381.1 | F294: 0.01K | G294: 0
A295: 43874 | B295: 305.9 | C295: 306.4 | D295: 306.7 | E295: 306.4 | F295: 0.02K | G295: 0
A296: 43875 | B296: 305.9 | C296: 306.4 | D296: 306.7 | E296: 306.4 | F296: 0.03K | G296: 0
A297: 43878 | B297: 305.95 | C297: 306.4 | D297: 306.7 | E297: 306.4 | F297: 0.02K | G297: 0.0002
A298: 43879 | B298: 305.95 | C298: 306.45 | D298: 306.7 | E298: 306.425 | F298: 0.02K | G298: 0
A299: 43880 | B299: 305.95 | C299: 306.7 | D299: 306.7 | E299: 306.4 | F299: 0.01K | G299: 0
A300: 43881 | B300: 306 | C300: 306.45 | D300: 307.25 | E300: 306.4 | F300: 0.05K | G300: 0.0002
A301: 43882 | B301: 306 | C301: 306.5 | D301: 306.725 | E301: 306.4 | F301: 0.02K | G301: 0
A302: 43885 | B302: 306 | C302: 306.5 | D302: 306.725 | E302: 306.45 | F302: 0.01K | G302: 0
A303: 43886 | B303: 305.92 | C303: 306.5 | D303: 307.2 | E303: 306.41 | F303: 0.02K | G303: -0.0003
A304: 43887 | B304: 305.95 | C304: 306.42 | D304: 306.7 | E304: 306.42 | F304: 0.02K | G304: 0.0001
... A306: 43889 | B306: 305.9 | C306: 306.45 | D306: 306.7 | E306: 306.4 | F306: 0.01K | G306: -0.0002
A307: 43891 | B307: 306 | C307: 307.5 | D307: 307.5 | E307: 306.45 | G307: -0.0033
A308: 43892 | B308: 306 | C308: 306.5 | D308: 306.725 | E308: 306.425 | F308: 0.01K | G308: 0
A309: 43893 | B309: 306 | C309: 306.45 | D309: 306.725 | E309: 306.45 | F309: 0.02K | G309: 0.0002
A310: 43894 | B310: 360 | C310: 360.5 | D310: 361.25 | E310: 360.5 | F310: 0.01K | G310: 0
A311: 43896 | B311: 360 | C311: 360.5 | D311: 361.25 | E311: 360.5 | F311: 0.01K | G311: 0
A312: 43897 | B312: 360 | C312: 360.5 | D312: 360.5 | E312: 360.5 | G312: 0
A313: 43898 | B313: 380.5 | C313: 381 | D313: 381.25 | E313: 380.25 | F313: 0.01K | G313: 0
A314: 43899 | B314: 380.7 | C314: 381.2 | D314: 381.35 | E314: 380.25 | F314: 0.01K | G314: 0
A315: 43901 | B315: 380.7 | C315: 381.2 | D315: 381.2 | E315: 381.2 | G315: 0
A316: 43902 | B316: 380.7 | C316: 381.2 | D316: 381.2 | E316: 381.2 | G316: 0
A317: 43903 | B317: 306 | C317: 306.45 | D317: 306.725 | E317: 306.425 | F317: 0.03K | G317: 0.0002
A318: 43906 | B318: 306 | C318: 306.5 | D318: 306.725 | E318: 306.45 | F318: 0.01K | G318: 0
A319: 43907 | B319: 305.95 | C319: 306.5 | D319: 306.725 | E319: 305.55 | F319: 0.02K | G319: -0.0002
A320: 43908 | B320: 306 | C320: 306.45 | D320: 306.725 | E320: 306.45 | F320: 0.01K | G320: 0.0002
A321: 43909 | B321: 306 | C321: 306.5 | D321: 306.725 | E321: 306.475 | F321: 0.01K | G321: 0
A322: 43910 | B322: 306 | C322: 306.5 | D322: 306.75 | E322: 305.55 | F322: 0.02K | G322: 0
A323: 43913 | B323: 372 | C323: 306.5 | D323: 372.25 | E323: 306.45 | F323: 0.01K | G323: 0.2157
A324: 43914 | B324: 360 | C324: 359.75 | D324: 380.25 | E324: 359.75 | F324: 0.00K | G324: -0.0323
A325: 43915 | B325: 360 | C325: 360.5 | D325: 360.5 | E325: 360.5 | G325: 0
A326: 43916 | B326: 360 | C326: 360.5 | D326: 361.25 | E326: 360.25 | F326: 0.01K | G326: 0
A327: 43917 | B327: 360 | C327: 360.5 | D327: 361.25 | E327: 360.5 | F327: 0.00K | G327: 0
A328: 43920 | B328: 360 | C328: 360.5 | D328: 361.25 | E328: 360.5 | F328: 0.01K | G328: 0
A329: 43921 | B329: 360 | C329: 360.5 | D329: 361.25 | E329: 360.5 | F329: 0.00K | G329: 0
A330: 43923 | B330: 306 | C330: 306.7 | D330: 307.25 | E330: 306.45 | F330: 0.03K | G330: 0
A331: 43924 | B331: 306 | C331: 306.5 | D331: 307.25 | E331: 306.475 | F331: 0.01K | G331: 0
A332: 43926 | B332: 360 | C332: 360.5 | D332: 360.5 | E332: 360.5 | G332: 0
A333: 43927 | B333: 360 | C333: 360.5 | D333: 361.25 | E333: 360.5 | F333: 0.01K | G333: 0
A334: 43929 | B334: 380.5 | C334: 381 | D334: 381.25 | E334: 380.25 | F334: 0.01K | G334: 0
A335: 43930 | B335: 380.7 | C335: 381.2 | D335: 381.35 | E335: 380.25 | F335: 0.01K | G335: 0
A336: 43932 | B336: 380.7 | C336: 381.2 | D336: 381.35 | E336: 381.1 | F336: 0.00K | G336: 0
A337: 43933 | B337: 380.7 | C337: 381.2 | D337: 381.2 | E337: 380.75 | F337: 0.01K | G337: 0
A338: 43934 | B338: 360 | C338: 360.5 | D338: 360.5 | E338: 360.5 | G338: 0
A339: 43935 | B339: 360 | C339: 360.5 | D339: 360.5 | E339: 360.5 | G339: 0
A340: 43936 | B340: 360 | C340: 360.5 | D340: 360.5 | E340: 360.5 | G340: 0
A341: 43937 | B341: 360 | C341: 360.5 | D341: 360.5 | E341: 360.25 | F341: 0.01K | G341: 0
A342: 43938 | B342: 360 | C342: 360.5 | D342: 360.5 | E342: 360.5 | G342: 0
A343: 43941 | B343: 360 | C343: 360.5 | D343: 361.25 | E343: 360.5 | F343: 0.01K | G343: 0
A344: 43942 | B344: 360 | C344: 360.5 | D344: 361.25 | E344: 360.25 | F344: 0.01K | G344: 0
A345: 43943 | B345: 360 | C345: 360.5 | D345: 360.5 | E345: 360.5 | G345: 0
A346: 43944 | B346: 360 | C346: 360.5 | D346: 360.5 | E346: 360.5 | G346: 0
A347: 43945 | B347: 360 | C347: 360.5 | D347: 361.5 | E347: 360.25 | F347: 0.01K | G347: 0
A348: 43948 | B348: 360 | C348: 360.5 | D348: 360.5 | E348: 360.5 | G348: 0
A349: 43949 | B349: 360 | C349: 360.5 | D349: 360.5 | E349: 360.5 | G349: 0
A350: 43950 | B350: 360 | C350: 360.5 | D350: 360.5 | E350: 360.5 | G350: 0
...
